{"is_source_file": true, "format": "TypeScript/TSX", "description": "A React functional component representing the 'Reports' page, displaying a heading and a placeholder message.", "external_files": [], "external_methods": [], "published": [], "classes": [], "methods": [{"name": "ReportsPage", "description": "React functional component rendering the Reports page UI."}], "calls": [], "search-terms": ["ReportsPage", "React", "TSX", "frontend", "page component"], "state": 2, "file_id": 33, "knowledge_revision": 70, "git_revision": "", "ctags": [], "hash": "6f9aeef571415f5578b0180ed7a5c3a9", "format-version": 4, "code-base-name": "saas_frontend", "filename": "saas_frontend/src/app/(protected)/reports/page.tsx", "revision_history": [{"70": ""}]}